mytorch/__init__.py
mytorch/dataiters.py
mytorch/loops.py
mytorch/lriters.py
mytorch/metrics.py
mytorch/nlutils.py
mytorch/utils/__init__.py
mytorch/utils/goodies.py
my_torch-0.0.13.dist-info/LICENSE
my_torch-0.0.13.dist-info/METADATA
my_torch-0.0.13.dist-info/WHEEL
my_torch-0.0.13.dist-info/top_level.txt
my_torch-0.0.13.dist-info/RECORD
