Metadata-Version: 2.1
Name: my-torch
Version: 0.0.13
Summary: A transparent boilerplate + bag of tricks to ease my (yours?) (our?) PyTorch dev time.
Home-page: https://github.com/geraltofrivia/mytorch/
Author: Priyansh Trivedi
Author-email: mail@priyansh.page
License: UNKNOWN
Project-URL: Source Code, https://github.com/geraltofrivia/mytorch
Keywords: deep learning,pytorch,boilerplate,machine learning,neural network,preprocessing
Platform: UNKNOWN
Classifier: Development Status :: 1 - Planning
Classifier: Programming Language :: Python :: 3
Classifier: Operating System :: Unix
License-File: LICENSE
Requires-Dist: spacy
Requires-Dist: tqdm
Requires-Dist: numpy
